CHANGELOG.md
MANIFEST.in
README.rst
requirements.txt
setup.py
tox.ini
ff_tool.egg-info/PKG-INFO
ff_tool.egg-info/SOURCES.txt
ff_tool.egg-info/dependency_links.txt
ff_tool.egg-info/entry_points.txt
ff_tool.egg-info/not-zip-safe
ff_tool.egg-info/requires.txt
ff_tool.egg-info/top_level.txt
fftool/__init__.py
fftool/arg_parser.py
fftool/firefox_download.py
fftool/firefox_env_handler.py
fftool/firefox_install.py
fftool/firefox_profile.py
fftool/firefox_run.py
fftool/firefox_uninstall.py
fftool/hdiutil.py
fftool/main.py
fftool/configs/channels.ini
fftool/configs/darwin.ini
fftool/configs/linux.ini
fftool/configs/prefs.ini
fftool/configs/windows.ini