Metadata-Version: 1.1
Name: ff-tool
Version: 0.1.1
Summary: Firefox browser CLI test setup tool
Home-page: UNKNOWN
Author: Johnny Quest
Author-email: cloud-services-qa@mozilla.org
License: MPL2
Keywords: [firefox,test,pref,profile,download,install]
Platform: UNKNOWN
Classifier: Topic :: Software Development :: Quality Assurance
Classifier: Topic :: Software Development :: Testing
Classifier: Programming Language :: Python
Classifier: Programming Language :: Python :: 2.7
